sytorch/_eps.pyi
sytorch/_typing.pyi
sytorch/_types.pyi
sytorch/_einsum.pyi
sytorch/__init__.cpython-312-x86_64-linux-gnu.so
sytorch/_tensor.pyi
sytorch/__init__.pyi
sytorch/utils/array.pyi
sytorch/utils/core.pyi
sytorch/utils/_dispatch.pyi
sytorch/utils/_jacobian.pyi
sytorch/utils/__init__.pyi
sytorch/utils/logging.pyi
sytorch/utils/_rich/spinner.pyi
sytorch/utils/_rich/status.pyi
sytorch/utils/_rich/__init__.pyi
sytorch/nn/_symbolic_mode.pyi
sytorch/nn/parameter.pyi
sytorch/nn/__init__.pyi
sytorch/nn/modules/activation.pyi
sytorch/nn/modules/graph_module.pyi
sytorch/nn/modules/container.pyi
sytorch/nn/modules/linear.pyi
sytorch/nn/modules/module.pyi
sytorch/nn/modules/__init__.pyi
sytorch/nn/functional/activation.pyi
sytorch/nn/functional/linear.pyi
sytorch/nn/functional/__init__.pyi
sytorch-0.1.8.dist-info/WHEEL
sytorch-0.1.8.dist-info/RECORD
sytorch-0.1.8.dist-info/top_level.txt
sytorch-0.1.8.dist-info/METADATA
sytorch-0.1.8.dist-info/licenses/LICENSE.txt
