Metadata-Version: 2.4
Name: sytorch
Version: 0.1.8
Summary: A symbolic PyTorch library with solver and verifier backends.
Home-page: https://sytorch.org/
Author: Zhe Tao
Author-email: zhetao@ucdavis.edu
License: Proprietary
Project-URL: Documentation, https://sytorch.org/
Platform: any
Classifier: Development Status :: 4 - Beta
Classifier: Programming Language :: Python
License-File: LICENSE.txt
Requires-Dist: importlib-metadata; python_version < "3.8"
Requires-Dist: torch>=2.5.0
Requires-Dist: numpy<2.0.0
Requires-Dist: scipy
Requires-Dist: gurobipy>=12.0.0
Requires-Dist: captum
Requires-Dist: rich
Requires-Dist: tabulate
Requires-Dist: requests
Requires-Dist: cryptography
Requires-Dist: py7zr
Provides-Extra: testing-requires
Requires-Dist: setuptools; extra == "testing-requires"
Requires-Dist: pytest; extra == "testing-requires"
Requires-Dist: pytest-cov; extra == "testing-requires"
Dynamic: license-file
